cmc/__init__.py
cmc/service/__init__.py
cmc/token/__init__.py
cmc/worker/__init__.py
docs/__init__.py
py_coinmarketcap-0.0.2.dist-info/METADATA
py_coinmarketcap-0.0.2.dist-info/RECORD
py_coinmarketcap-0.0.2.dist-info/WHEEL
py_coinmarketcap-0.0.2.dist-info/top_level.txt
